edc_he/.DS_Store
edc_he/__init__.py
edc_he/admin/__init__.py
edc_he/admin/assets_admin.py
edc_he/admin/household_head_admin.py
edc_he/admin/income_admin.py
edc_he/admin/patient_admin.py
edc_he/admin/property_admin.py
edc_he/admin.py
edc_he/admin_site.py
edc_he/apps.py
edc_he/auth_objects.py
edc_he/auths.py
edc_he/calculators.py
edc_he/choices.py
edc_he/constants.py
edc_he/fieldsets.py
edc_he/form_validators/__init__.py
edc_he/form_validators/assets_form_validator.py
edc_he/form_validators/household_head_form_validator.py
edc_he/form_validators/income_form_validator.py
edc_he/form_validators/patient_form_validator.py
edc_he/form_validators/property_form_validator.py
edc_he/form_validators/simple/__init__.py
edc_he/form_validators/simple/simple_form_validator.py
edc_he/forms/__init__.py
edc_he/forms/assets_form.py
edc_he/forms/education_form.py
edc_he/forms/household_head.py
edc_he/forms/income_form.py
edc_he/forms/modelform_mixins.py
edc_he/forms/patient_form.py
edc_he/forms/property_form.py
edc_he/list_data.py
edc_he/locale/.DS_Store
edc_he/locale/lg/LC_MESSAGES/django.po
edc_he/locale/sw/.DS_Store
edc_he/locale/sw/LC_MESSAGES/.DS_Store
edc_he/locale/sw/LC_MESSAGES/django.mo
edc_he/locale/sw/LC_MESSAGES/django.po
edc_he/migrations/0001_initial.py
edc_he/migrations/0002_historicalreligions_historicalnationalities_and_more.py
edc_he/migrations/0003_ethnicities_extra_value_and_more.py
edc_he/migrations/0004_historicalemployment_historicaleducation_employment_and_more.py
edc_he/migrations/0005_rename_employment_employmenttype_and_more.py
edc_he/migrations/0006_alter_education_options_alter_employmenttype_options_and_more.py
edc_he/migrations/0007_remove_education_edc_he_educ_name_64c0c9_idx_and_more.py
edc_he/migrations/0008_healtheconomics_alter_education_extra_value_and_more.py
edc_he/migrations/0009_rename_education_educationtype_and_more.py
edc_he/migrations/0010_delete_historicaleducationtype.py
edc_he/migrations/0011_historicaleducation_education.py
edc_he-1.5.4.dist-info/licenses/LICENSE
edc_he-1.5.4.dist-info/WHEEL
edc_he-1.5.4.dist-info/METADATA
edc_he-1.5.4.dist-info/RECORD
